{          
    "success": true,
    "timestamp": 1718739664,
    "base": "EUR",
    "date": "2024-06-18",
    "rates": {
        "AED": 3.94406,
        "AFN": 75.165257,
        "ALL": 100.70499,
        "AMD": 417.416691,
        "ANG": 1.935579,
        "AOA": 919.711794,
        "ARS": 972.591166,
        "AUD": 1.61364,
        "AWG": 1.932834,
        "AZN": 1.821776,
        "BAM": 1.95969,
        "BBD": 2.168425,
        "BDT": 126.191688,
        "BGN": 1.95624,
        "BHD": 0.404718,
        "BIF": 3094.145124,
        "BMD": 1.073797,
        "BND": 1.453971,
        "BOB": 7.42087,
        "BRL": 5.836189,
        "BSD": 1.073942,
        "BTC": 0.000016632646,
        "BTN": 89.56477,
        "BWP": 14.543142,
        "BYN": 3.513898,
        "BYR": 21046.414861,
        "BZD": 2.164838,
        "CAD": 1.473088,
        "CDF": 3049.58259,
        "CHF": 0.949126,
        "CLF": 0.036402,
        "CLP": 1004.440292,
        "CNY": 7.78997,
        "CNH": 7.808639,
        "COP": 4453.571716,
        "CRC": 564.325542,
        "CUC": 1.073797,
        "CUP": 28.455612,
        "CVE": 110.655232,
        "CZK": 24.825128,
        "DJF": 190.835049,
        "DKK": 7.459881,
        "DOP": 63.574737,
        "DZD": 144.529899,
        "EGP": 51.231806,
        "ERN": 16.10695,
        "ETB": 61.74121,
        "EUR": 1,
        "FJD": 2.427316,
        "FKP": 0.842503,
        "GBP": 0.844969,
        "GEL": 3.076449,
        "GGP": 0.842503,
        "GHS": 16.215783,
        "GIP": 0.842503,
        "GMD": 72.75007,
        "GNF": 9234.651625,
        "GTQ": 8.333699,
        "GYD": 224.600054,
        "HKD": 8.383077,
        "HNL": 26.957685,
        "HRK": 7.536375,
        "HTG": 142.303824,
        "HUF": 394.44841,
        "IDR": 17576.279831,
        "ILS": 3.991254,
        "IMP": 0.842503,
        "INR": 89.516413,
        "IQD": 1406.673646,
        "IRR": 45193.418056,
        "ISK": 149.300577,
        "JEP": 0.842503,
        "JMD": 166.911349,
        "JOD": 0.761208,
        "JPY": 169.473,
        "KES": 138.519461,
        "KGS": 94.066306,
        "KHR": 4416.472009,
        "KMF": 492.711289,
        "KPW": 966.41715,
        "KRW": 1482.156173,
        "KWD": 0.329312,
        "KYD": 0.895002,
        "KZT": 493.849577,
        "LAK": 23564.467913,
        "LBP": 96212.18194,
        "LKR": 327.560265,
        "LRD": 208.533197,
        "LSL": 19.500376,
        "LTL": 3.170642,
        "LVL": 0.649529,
        "LYD": 5.208007,
        "MAD": 10.73528,
        "MDL": 19.181436,
        "MGA": 4805.239905,
        "MKD": 61.642077,
        "MMK": 3487.649719,
        "MNT": 3704.598639,
        "MOP": 8.636486,
        "MRU": 42.394001,
        "MUR": 50.113815,
        "MVR": 16.531122,
        "MWK": 1862.475634,
        "MXN": 19.773102,
        "MYR": 5.061836,
        "MZN": 68.395522,
        "NAD": 19.500346,
        "NGN": 1600.495208,
        "NIO": 39.548083,
        "NOK": 11.370467,
        "NPR": 143.290114,
        "NZD": 1.74733,
        "OMR": 0.413354,
        "PAB": 1.073952,
        "PEN": 4.073443,
        "PGK": 4.128772,
        "PHP": 62.96743,
        "PKR": 299.054554,
        "PLN": 4.338172,
        "PYG": 8077.034344,
        "QAR": 3.909152,
        "RON": 4.975434,
        "RSD": 117.066547,
        "RUB": 91.674524,
        "RWF": 1404.526053,
        "SAR": 4.028713,
        "SBD": 9.070497,
        "SCR": 16.143176,
        "SDG": 645.889776,
        "SEK": 11.209863,
        "SGD": 1.450876,
        "SHP": 1.356688,
        "SLE": 24.533358,
        "SLL": 22516.981468,
        "SOS": 613.13768,
        "SRD": 33.535756,
        "STD": 22225.423219,
        "SVC": 9.397744,
        "SYP": 2697.946822,
        "SZL": 19.500562,
        "THB": 39.36572,
        "TJS": 11.491627,
        "TMT": 3.769026,
        "TND": 3.3621,
        "TOP": 2.535717,
        "TRY": 34.989233,
        "TTD": 7.295619,
        "TWD": 34.745887,
        "TZS": 2807.978047,
        "UAH": 43.586934,
        "UGX": 3992.926667,
        "USD": 1.073797,
        "UYU": 42.184136,
        "UZS": 13583.52799,
        "VEF": 3889884.872282,
        "VES": 39.016244,
        "VND": 27328.125419,
        "VUV": 127.483263,
        "WST": 3.007291,
        "XAF": 657.274047,
        "XAG": 0.036338,
        "XAU": 0.000461,
        "XCD": 2.90199,
        "XDR": 0.815054,
        "XOF": 657.701582,
        "XPF": 119.331742,
        "YER": 268.825023,
        "ZAR": 19.386116,
        "ZMK": 9665.43794,
        "ZMW": 27.735577,
        "ZWL": 345.762092
    }
}
{"symbols":"EUR,USD,CAD,GBP,JPY,CNY,AUD,HKD,IDR,MXN,SGD,KRW,THB,TWD"}
{"CAD":"CANADIAN DOLLAR","GBP": "BRITISH POUND","EUR": "EURO", "JPY": "JAPANESE YEN","CNY": "CHINESE YUAN","AUD": "AUSTRALIAN DOLLAR", "HKD": "HONG KONG DOLLAR","IDR": "INDONESIAN RUPIAH","MXN": "MEXICAN PESO","SGD": "SINGAPORE DOLLAR","KRW": "SOUTH KOREAN WON","THB": "THAI BAHT","TWD": "NEW TAIWAN DOLLAR","USD": "US DOLLAR"}